{
	"timedOutput_events":[
		{
			"time":0900,
			"type":"pwm",
			"pwmStates":[
				{"channel":0,"value":3900},
				{"channel":1,"value":3800},
				{"channel":2,"value":3700}
			]
		},
		{
			"time":0900,
			"type":"io",
			"ioStates":[
				{"pin":38,"value":0}
			]
		},
		{
			"time":2230,
			"type":"pwm",
			"pwmStates":[
				{"channel":0,"value":1950},
				{"channel":1,"value":1850},
				{"channel":2,"value":1800}
			]
		},
		{
			"time":2300,
			"type":"pwm",
			"pwmStates":[
				{"channel":0,"value":0},
				{"channel":1,"value":0},
				{"channel":2,"value":0}
			]
		},
		{
			"time":2230,
			"type":"io",
			"ioStates":[
				{"pin":38,"value":1}
			]
		}
	]
}